[{"__symbolic":"module","version":4,"metadata":{"DxoValueIndicatorComponent":{"__symbolic":"class","extends":{"__symbolic":"reference","module":"./base/gauge-indicator","name":"DxoGaugeIndicator","line":59,"character":48},"decorators":[{"__symbolic":"call","expression":{"__symbolic":"reference","module":"@angular/core","name":"Component","line":32,"character":1},"arguments":[{"selector":"dxo-value-indicator","template":"","styles":[""],"providers":[{"__symbolic":"reference","module":"../../core/nested-option","name":"NestedOptionHost","line":36,"character":16}],"inputs":["arrowLength","backgroundColor","baseValue","beginAdaptingAtRadius","color","horizontalOrientation","indentFromCenter","length","offset","palette","secondColor","secondFraction","size","spindleGapSize","spindleSize","text","type","verticalOrientation","width"]}]}],"members":{"__ctor__":[{"__symbolic":"constructor","parameterDecorators":[[{"__symbolic":"call","expression":{"__symbolic":"reference","module":"@angular/core","name":"SkipSelf","line":66,"character":17}},{"__symbolic":"call","expression":{"__symbolic":"reference","module":"@angular/core","name":"Host","line":66,"character":29}}],[{"__symbolic":"call","expression":{"__symbolic":"reference","module":"@angular/core","name":"Host","line":67,"character":13}}]],"parameters":[{"__symbolic":"reference","module":"../../core/nested-option","name":"NestedOptionHost","line":66,"character":54},{"__symbolic":"reference","module":"../../core/nested-option","name":"NestedOptionHost","line":66,"character":54}]}]}},"DxoValueIndicatorModule":{"__symbolic":"class","decorators":[{"__symbolic":"call","expression":{"__symbolic":"reference","module":"@angular/core","name":"NgModule","line":75,"character":1},"arguments":[{"declarations":[{"__symbolic":"reference","name":"DxoValueIndicatorComponent"}],"exports":[{"__symbolic":"reference","name":"DxoValueIndicatorComponent"}]}]}]}}}]